natural_selector/__init__.py
natural_selector/api.py
natural_selector/_internal/__init__.py
natural_selector/_internal/ir/__init__.py
natural_selector/_internal/ir/nodes.py
natural_selector/_internal/parsers/__init__.py
natural_selector/_internal/parsers/cdp_parser.py
natural_selector/_internal/rag/chunker.py
natural_selector/_internal/rag/embedder.py
natural_selector/_internal/rag/llm.py
natural_selector/_internal/rag/markdown_serializer.py
natural_selector/_internal/rag/retriever.py
natural_selector/_internal/selector/__init__.py
natural_selector/_internal/selector/generator.py
natural_selector/_internal/selector/id_mapping.py
natural_selector/_internal/transforms/__init__.py
natural_selector/_internal/transforms/add_identifiers.py
natural_selector/_internal/transforms/semantic.py
natural_selector/_internal/transforms/visibility.py
natural_selector/_internal/transforms/semantic_steps/__init__.py
natural_selector/_internal/transforms/semantic_steps/collapse_wrappers.py
natural_selector/_internal/transforms/semantic_steps/filter_by_attributes.py
natural_selector/_internal/transforms/semantic_steps/filter_by_tags.py
natural_selector/_internal/transforms/semantic_steps/filter_empty_nodes.py
natural_selector/integrations/__init__.py
natural_selector/integrations/openai_embedder.py
natural_selector/integrations/openai_llm.py
natural_selector/interfaces/__init__.py
natural_selector/interfaces/embedder.py
natural_selector/interfaces/llm.py
natural_selector/utils/__init__.py
natural_selector/utils/snapshot.py
natural_selector-0.1.0.dist-info/licenses/LICENSE
natural_selector-0.1.0.dist-info/METADATA
natural_selector-0.1.0.dist-info/WHEEL
natural_selector-0.1.0.dist-info/top_level.txt
natural_selector-0.1.0.dist-info/RECORD
