Metadata-Version: 2.4
Name: natural-selector
Version: 0.1.0
Summary: Natural language HTML selector engine
Author-email: Steve Wang <stevewang.at.work@gmail.com>
License: MIT
Keywords: selector,dom,natural-language,browser-automation,html
Classifier: Development Status :: 3 - Alpha
Classifier: Intended Audience :: Developers
Classifier: License :: OSI Approved :: MIT License
Classifier: Programming Language :: Python :: 3
Classifier: Programming Language :: Python :: 3.8
Classifier: Programming Language :: Python :: 3.9
Classifier: Programming Language :: Python :: 3.10
Classifier: Programming Language :: Python :: 3.11
Requires-Python: >=3.8
License-File: LICENSE
Requires-Dist: tiktoken>=0.5.0
Requires-Dist: numpy>=1.24.0
Provides-Extra: default-embedder
Requires-Dist: sentence-transformers>=2.2.0; extra == "default-embedder"
Provides-Extra: openai
Requires-Dist: openai>=1.0.0; extra == "openai"
Requires-Dist: python-dotenv>=1.0.0; extra == "openai"
Provides-Extra: dev
Requires-Dist: pytest>=7.0; extra == "dev"
Requires-Dist: black>=23.0; extra == "dev"
Requires-Dist: mypy>=1.0; extra == "dev"
Requires-Dist: ruff>=0.1.0; extra == "dev"
Dynamic: license-file
